andleeb_drf_auto_crud/__init__.py
andleeb_drf_auto_crud/model.py
andleeb_drf_auto_crud/serializer.py
andleeb_drf_auto_crud/url.py
andleeb_drf_auto_crud/view.py
andleeb_drf_auto_crud-1.0.1.dist-info/METADATA
andleeb_drf_auto_crud-1.0.1.dist-info/WHEEL
andleeb_drf_auto_crud-1.0.1.dist-info/top_level.txt
andleeb_drf_auto_crud-1.0.1.dist-info/RECORD
