Metadata-Version: 2.4
Name: andleeb-drf-auto-crud
Version: 1.0.1
Summary: Automatic CRUD API generator for Django models using DRF, dynamic and reusable.
Author: Andleeb Miraan
License: MIT
Keywords: django,djangorestframework,drf,crud,auto-crud,api
Classifier: Framework :: Django
Classifier: Framework :: Django :: 5.2
Classifier: Programming Language :: Python :: 3
Classifier: Programming Language :: Python :: 3.11
Classifier: License :: OSI Approved :: MIT License
Classifier: Operating System :: OS Independent
Requires-Python: >=3.11
Requires-Dist: Django>=5.2.6
Requires-Dist: djangorestframework>=3.16.1
Requires-Dist: inflect>=7.5.0
